neuropop/__init__.py
neuropop/dimensionality.py
neuropop/filtering.py
neuropop/future_prediction.py
neuropop/linear_prediction.py
neuropop/nn_prediction.py
neuropop/peer_prediction.py
neuropop/split_data.py
neuropop/utils.py
neuropop-1.0.1.dist-info/LICENSE
neuropop-1.0.1.dist-info/METADATA
neuropop-1.0.1.dist-info/WHEEL
neuropop-1.0.1.dist-info/top_level.txt
neuropop-1.0.1.dist-info/RECORD
