Metadata-Version: 2.1
Name: neuropop
Version: 1.0.1
Summary: analysis tools for neural population recordings
Home-page: https://github.com/MouseLand/neuropop
Author: Marius Pachitariu and Carsen Stringer
Author-email: stringerc@janelia.hhmi.org
Classifier: Programming Language :: Python :: 3
Classifier: License :: OSI Approved :: GNU General Public License v3 (GPLv3)
Classifier: Operating System :: OS Independent
License-File: LICENSE
Requires-Dist: numpy (>=1.20.0)
Requires-Dist: scipy
Requires-Dist: natsort
Requires-Dist: torch (>=1.6)
Requires-Dist: scikit-learn
